soulmate_sketch/__init__.py
soulmate_sketch-0.1.dist-info/METADATA
soulmate_sketch-0.1.dist-info/WHEEL
soulmate_sketch-0.1.dist-info/top_level.txt
soulmate_sketch-0.1.dist-info/RECORD
