Metadata-Version: 2.1
Name: soulmate_sketch
Version: 0.1
Summary: Discover Your True Love with a Psychic Soulmate Sketch
Home-page: https://www.thesoulmatesketcher.com
Author: Luna
Author-email: thesoulmatesketcher@gmail.com
Classifier: Programming Language :: Python :: 3
Classifier: License :: OSI Approved :: MIT License
Classifier: Operating System :: OS Independent
Requires-Python: >=3.6
